lark/__init__.py
lark/cli.py
lark/detector.py
lark/model.py
lark/onnx_detector.py
lark/tokenizer.py
lark_language_detector-1.2.0.dist-info/METADATA
lark_language_detector-1.2.0.dist-info/WHEEL
lark_language_detector-1.2.0.dist-info/entry_points.txt
lark_language_detector-1.2.0.dist-info/top_level.txt
lark_language_detector-1.2.0.dist-info/RECORD
