Metadata-Version: 2.4
Name: lark-language-detector
Version: 1.2.0
Summary: A lightweight language detection library similar to fasttext and Google's implementation with ONNX support
Home-page: https://github.com/your-username/lark-language-detector
Author: Farshore Team
Author-email: your-email@example.com
Keywords: language-detection,nlp,machine-learning,ai,onnx
Classifier: Development Status :: 4 - Beta
Classifier: Intended Audience :: Developers
Classifier: License :: OSI Approved :: MIT License
Classifier: Operating System :: OS Independent
Classifier: Programming Language :: Python :: 3
Classifier: Programming Language :: Python :: 3.7
Classifier: Programming Language :: Python :: 3.8
Classifier: Programming Language :: Python :: 3.9
Classifier: Programming Language :: Python :: 3.10
Classifier: Programming Language :: Python :: 3.11
Classifier: Topic :: Scientific/Engineering :: Artificial Intelligence
Classifier: Topic :: Text Processing :: Linguistic
Requires-Python: >=3.7
Requires-Dist: requests>=2.25.0
Requires-Dist: numpy>=1.21.0
Requires-Dist: zhconv>=1.4.0
Requires-Dist: onnxruntime>=1.14.0
Dynamic: author
Dynamic: author-email
Dynamic: classifier
Dynamic: description
Dynamic: description-content-type
Dynamic: home-page
Dynamic: keywords
Dynamic: requires-dist
Dynamic: requires-python
Dynamic: summary
